torchtree/__init__.py
torchtree/_version.py
torchtree/torchtree.py
torchtree/typing.py
torchtree/cli/__init__.py
torchtree/cli/advi.py
torchtree/cli/argparse_utils.py
torchtree/cli/cli.py
torchtree/cli/evolution.py
torchtree/cli/hmc.py
torchtree/cli/jacobians.py
torchtree/cli/loggers.py
torchtree/cli/map.py
torchtree/cli/mcmc.py
torchtree/cli/operators.py
torchtree/cli/plugin.py
torchtree/cli/plugin_manager.py
torchtree/cli/priors.py
torchtree/cli/utils.py
torchtree/core/__init__.py
torchtree/core/abstractparameter.py
torchtree/core/classproperty_decorator.py
torchtree/core/container.py
torchtree/core/identifiable.py
torchtree/core/logger.py
torchtree/core/model.py
torchtree/core/parameter.py
torchtree/core/parameter_encoder.py
torchtree/core/parameter_utils.py
torchtree/core/parametric.py
torchtree/core/runnable.py
torchtree/core/serializable.py
torchtree/core/utils.py
torchtree/distributions/__init__.py
torchtree/distributions/bayesian_bridge.py
torchtree/distributions/ctmc_scale.py
torchtree/distributions/deterministic_normal.py
torchtree/distributions/distributions.py
torchtree/distributions/gmrf.py
torchtree/distributions/gmrf_integrated.py
torchtree/distributions/inverse_gamma.py
torchtree/distributions/joint_distribution.py
torchtree/distributions/log_normal.py
torchtree/distributions/multivariate_normal.py
torchtree/distributions/normal.py
torchtree/distributions/one_on_x.py
torchtree/distributions/scale_mixture.py
torchtree/distributions/transforms.py
torchtree/distributions/tree_prior.py
torchtree/evolution/__init__.py
torchtree/evolution/alignment.py
torchtree/evolution/attribute_pattern.py
torchtree/evolution/bdsk.py
torchtree/evolution/birth_death.py
torchtree/evolution/branch_model.py
torchtree/evolution/coalescent.py
torchtree/evolution/datatype.py
torchtree/evolution/io.py
torchtree/evolution/poisson_tree_likelihood.py
torchtree/evolution/rate_transform.py
torchtree/evolution/root_transform.py
torchtree/evolution/site_model.py
torchtree-1.0.2.dist-info/LICENSE
torchtree-1.0.2.dist-info/METADATA
torchtree-1.0.2.dist-info/WHEEL
torchtree-1.0.2.dist-info/entry_points.txt
torchtree-1.0.2.dist-info/top_level.txt
torchtree-1.0.2.dist-info/RECORD
